repdex/__cli__.py
repdex/__init__.py
repdex/_version.py
repdex/conf/__init__.py
repdex/conf/about/repdex.yaml
repdex/py.typed
repdex-0.1.0.dist-info/LICENSE
repdex-0.1.0.dist-info/METADATA
repdex-0.1.0.dist-info/WHEEL
repdex-0.1.0.dist-info/entry_points.txt
repdex-0.1.0.dist-info/RECORD
